django_simple_publish_model/__init__.py
django_simple_publish_model/actions.py
django_simple_publish_model/admin.py
django_simple_publish_model/apps.py
django_simple_publish_model/models.py
django_simple_publish_model/requirements.txt
django_simple_publish_model/tests.py
django_simple_publish_model/views.py
django_simple_publish_model/locale/zh_Hans/LC_MESSAGES/django.mo
django_simple_publish_model/locale/zh_Hans/LC_MESSAGES/django.po
django_simple_publish_model/migrations/__init__.py
django_simple_publish_model-0.1.4.dist-info/LICENSE
django_simple_publish_model-0.1.4.dist-info/METADATA
django_simple_publish_model-0.1.4.dist-info/WHEEL
django_simple_publish_model-0.1.4.dist-info/top_level.txt
django_simple_publish_model-0.1.4.dist-info/RECORD
