Metadata-Version: 2.1
Name: django-simple-publish-model
Version: 0.1.4
Summary: Django application provides simple publish/unpublish model and admin.
Author: Yao Bin
Author-email: yaobin@zencore.cn
Maintainer: Yao Bin
Maintainer-email: yaobin@zencore.cn
License: MIT
Keywords: django abstract model,django simple publish model
Classifier: Development Status :: 5 - Production/Stable
Classifier: Intended Audience :: Developers
Classifier: Topic :: Software Development :: Libraries :: Python Modules
Classifier: License :: OSI Approved :: MIT License
Classifier: Programming Language :: Python :: 3
Classifier: Programming Language :: Python :: 3 :: Only
License-File: LICENSE
Requires-Dist: django-fastadmin >=0.7.0
